{"cameraMode":{"drawMode":0,"name":"Shaded","section":"Shading Mode"},"sceneLighting":true,"audioPlay":false,"sceneViewState":{"m_AlwaysRefresh":false,"showFog":true,"showSkybox":true,"showFlares":true,"showImageEffects":true,"showParticleSystems":true,"showVisualEffectGraphs":true,"m_FxEnabled":true},"in2DMode":false,"pivot":{"x":4.525991916656494,"y":-3.52335786819458,"z":7.766441345214844},"rotation":{"x":0.10419564694166184,"y":0.8178402781486511,"z":-0.1567019373178482,"w":0.5438091158866882},"size":7.487915992736816,"orthographic":false}