{"cameraMode":{"drawMode":0,"name":"Shaded","section":"Shading Mode"},"sceneLighting":false,"audioPlay":false,"sceneViewState":{"m_AlwaysRefresh":false,"showFog":true,"showSkybox":false,"showFlares":true,"showImageEffects":true,"showParticleSystems":true,"showVisualEffectGraphs":true,"m_FxEnabled":true},"in2DMode":false,"pivot":{"x":0.0510406494140625,"y":2.349112033843994,"z":-0.018677115440368654},"rotation":{"x":-0.25046175718307497,"y":-0.445966511964798,"z":0.1315242350101471,"w":-0.8491690158843994},"size":3.5197672843933107,"orthographic":false}